{
  "type": "minecraft:block",
  "pools": [
    {
      "rolls": 1.0,
      "bonus_rolls": 0.0,
      "entries": [
        {
          "type": "minecraft:item",
          "name": "mellow_revolution:corn_seeds"
        }
      ],
      "conditions": [
        {
          "condition": "minecraft:survives_explosion"
        }
      ]
    },
    {
      "rolls": 1.0,
      "bonus_rolls": 0.0,
      "entries": [
        {
          "type": "minecraft:item",
          "name": "mellow_revolution:corn"
        }
      ],
      "conditions": [
        {
          "condition": "minecraft:survives_explosion"
        },
        {
          "condition": "minecraft:block_state_property",
          "block": "mellow_revolution:corn_crop",
          "properties": {
            "growth": "bottom4"
          }
        }
      ],
      "functions": [
        {
          "function": "minecraft:apply_bonus",
          "enchantment": "minecraft:fortune",
          "formula": "minecraft:binomial_with_bonus_count",
          "parameters": {
            "extra": 3,
            "probability": 0.5
          }
        }
      ]
    },
    {
      "rolls": 1.0,
      "bonus_rolls": 0.0,
      "entries": [
        {
          "type": "minecraft:item",
          "name": "mellow_revolution:corn"
        }
      ],
      "conditions": [
        {
          "condition": "minecraft:survives_explosion"
        },
        {
          "condition": "minecraft:block_state_property",
          "block": "mellow_revolution:corn_crop",
          "properties": {
            "growth": "top0"
          }
        }
      ],
      "functions": [
        {
          "function": "minecraft:apply_bonus",
          "enchantment": "minecraft:fortune",
          "formula": "minecraft:binomial_with_bonus_count",
          "parameters": {
            "extra": 3,
            "probability": 0.625
          }
        }
      ]
    }
  ]
}